ChernoffFace/ChernoffFace.py
ChernoffFace/ChernoffFunctions.py
ChernoffFace/DataLoaders.py
ChernoffFace/__init__.py
ChernoffFace/resources/dfEmployeeAttitude.csv
ChernoffFace/resources/dfUSAArrests.csv
ChernoffFace-0.1.4.dist-info/LICENSE
ChernoffFace-0.1.4.dist-info/METADATA
ChernoffFace-0.1.4.dist-info/WHEEL
ChernoffFace-0.1.4.dist-info/top_level.txt
ChernoffFace-0.1.4.dist-info/RECORD
