Metadata-Version: 2.1
Name: ChernoffFace
Version: 0.1.4
Summary: Makes of Chernoff face diagrams.
Home-page: https://github.com/antononcube/Python-packages/tree/main/ChernoffFace
Author: Anton Antonov
Author-email: antononcube@posteo.net
License: UNKNOWN
Keywords: chernoff,face,chernoff face,chernoff face diagram,multi-dimensional,visualization
Platform: UNKNOWN
Classifier: Intended Audience :: Science/Research
Classifier: Programming Language :: Python :: 3
Classifier: License :: OSI Approved :: Artistic License
Classifier: Intended Audience :: Science/Research
Classifier: Operating System :: OS Independent
Requires-Python: >=3.7
License-File: LICENSE
Requires-Dist: numpy
Requires-Dist: matplotlib
Requires-Dist: pillow
